aiaccel/__init__.py
aiaccel/launcher.py
aiaccel/config/__init__.py
aiaccel/config/config.py
aiaccel/config/git.py
aiaccel/config/apps/__init__.py
aiaccel/config/apps/check_git.py
aiaccel/config/apps/get_value.py
aiaccel/hpo/__init__.py
aiaccel/hpo/algorithms/__init__.py
aiaccel/hpo/algorithms/nelder_mead_algorithm.py
aiaccel/hpo/apps/__init__.py
aiaccel/hpo/apps/optimize.py
aiaccel/hpo/apps/config/__init__.py
aiaccel/hpo/apps/config/default.yaml
aiaccel/hpo/optuna/__init__.py
aiaccel/hpo/optuna/hparams.py
aiaccel/hpo/optuna/hparams_manager.py
aiaccel/hpo/optuna/samplers/__init__.py
aiaccel/hpo/optuna/samplers/nelder_mead_sampler.py
aiaccel/job/apps/__init__.py
aiaccel/job/apps/local.py
aiaccel/job/apps/pbs.py
aiaccel/job/apps/sge.py
aiaccel/job/apps/slurm.py
aiaccel/job/apps/config/__init__.py
aiaccel/job/apps/config/local.yaml
aiaccel/job/apps/config/pbs.yaml
aiaccel/job/apps/config/sge.yaml
aiaccel/job/apps/config/slurm.yaml
aiaccel/torch/__init__.py
aiaccel/torch/apps/__init__.py
aiaccel/torch/apps/train.py
aiaccel/torch/apps/config/__init__.py
aiaccel/torch/apps/config/train_base.yaml
aiaccel/torch/apps/config/train_ddp.yaml
aiaccel/torch/datasets/__init__.py
aiaccel/torch/datasets/cached_dataset.py
aiaccel/torch/datasets/file_cached_dataset.py
aiaccel/torch/datasets/hdf5_dataset.py
aiaccel/torch/datasets/scatter_dataset.py
aiaccel/torch/functional/__init__.py
aiaccel/torch/functional/linear_sum_assignment.py
aiaccel/torch/h5py/__init__.py
aiaccel/torch/h5py/hdf5_writer.py
aiaccel/torch/lightning/__init__.py
aiaccel/torch/lightning/abci_environment.py
aiaccel/torch/lightning/ckpt.py
aiaccel/torch/lightning/opt_lightning_module.py
aiaccel/torch/lightning/callbacks/__init__.py
aiaccel/torch/lightning/callbacks/load_pretrained.py
aiaccel/torch/lightning/callbacks/print_unused_param.py
aiaccel/torch/lightning/callbacks/save_metric.py
aiaccel/torch/lightning/datamodules/__init__.py
aiaccel/torch/lightning/datamodules/single_datamodule.py
aiaccel-2026.2.0.dist-info/METADATA
aiaccel-2026.2.0.dist-info/WHEEL
aiaccel-2026.2.0.dist-info/entry_points.txt
aiaccel-2026.2.0.dist-info/licenses/LICENSE
aiaccel-2026.2.0.dist-info/licenses/LICENSE_HEADER
aiaccel-2026.2.0.dist-info/RECORD
