Metadata-Version: 2.4
Name: aiaccel
Version: 2026.2.0
Summary: AIST Toolkit for Accelerating Machine Learning Research
Project-URL: documentation, https://aistairc.github.io/aiaccel/
Project-URL: repository, https://github.com/aistairc/aiaccel
Author-email: AIST <onishi-masaki@aist.go.jp>
License: MIT
License-File: LICENSE
License-File: LICENSE_HEADER
Classifier: License :: OSI Approved :: MIT License
Requires-Python: >=3.10
Requires-Dist: attrs
Requires-Dist: colorama
Requires-Dist: h5py
Requires-Dist: huggingface-hub
Requires-Dist: hydra-core
Requires-Dist: lightning>=2.2.1
Requires-Dist: numpy
Requires-Dist: omegaconf
Requires-Dist: optuna>=4.5.0
Requires-Dist: rich
Requires-Dist: scipy
Requires-Dist: simpleeval
Requires-Dist: tensorboard
Requires-Dist: torch>=2.2.0
Requires-Dist: typing-extensions
Provides-Extra: dev
Requires-Dist: docstrfmt; extra == 'dev'
Requires-Dist: hatch; extra == 'dev'
Requires-Dist: matplotlib; extra == 'dev'
Requires-Dist: mypy; extra == 'dev'
Requires-Dist: myst-parser; extra == 'dev'
Requires-Dist: pandas; extra == 'dev'
Requires-Dist: pandas-stubs; extra == 'dev'
Requires-Dist: pre-commit; extra == 'dev'
Requires-Dist: pytest; extra == 'dev'
Requires-Dist: pytest-cov; extra == 'dev'
Requires-Dist: pytest-mock; extra == 'dev'
Requires-Dist: pytest-subprocess; extra == 'dev'
Requires-Dist: pytest-xdist; extra == 'dev'
Requires-Dist: ruff; extra == 'dev'
Requires-Dist: shibuya; extra == 'dev'
Requires-Dist: sphinx; extra == 'dev'
Requires-Dist: sphinx-autobuild; extra == 'dev'
Requires-Dist: sphinx-copybutton; extra == 'dev'
Requires-Dist: sphinx-design; extra == 'dev'
Requires-Dist: sphinx-fontawesome; extra == 'dev'
Requires-Dist: sphinx-intl; extra == 'dev'
Requires-Dist: sphinxcontrib-jquery; extra == 'dev'
Requires-Dist: types-colorama; extra == 'dev'
Requires-Dist: types-pyyaml; extra == 'dev'
Requires-Dist: types-toml; extra == 'dev'
Requires-Dist: undecorated; extra == 'dev'
Provides-Extra: github-actions
Requires-Dist: pytest-github-actions-annotate-failures; extra == 'github-actions'
